flytrap/__init__.py
flytrap/and_parser.py
flytrap/and_parser_test.py
flytrap/any_parser.py
flytrap/any_parser_test.py
flytrap/attempt_parser.py
flytrap/attempt_parser_test.py
flytrap/choice_parser.py
flytrap/choice_parser_test.py
flytrap/digit_parser.py
flytrap/digit_parser_test.py
flytrap/eof_parser.py
flytrap/eof_parser_test.py
flytrap/lazy_parser.py
flytrap/letter_parser.py
flytrap/letter_parser_test.py
flytrap/many1_parser.py
flytrap/many1_parser_test.py
flytrap/many_parser.py
flytrap/many_parser_test.py
flytrap/map_parser.py
flytrap/map_parser_test.py
flytrap/one_of_parser.py
flytrap/one_of_parser_test.py
flytrap/or_parser.py
flytrap/or_parser_test.py
flytrap/parser.py
flytrap/parser_exception.py
flytrap/skip_parser.py
flytrap/skip_parser_test.py
flytrap/space_parser.py
flytrap/space_parser_test.py
flytrap/split_by_parser.py
flytrap/split_by_parser_test.py
flytrap/string_parser.py
flytrap/string_parser_test.py
flytrap/take_parser.py
flytrap/take_parser_test.py
flytrap/token_parser.py
flytrap/token_parser_test.py
flytrap/until_parser.py
flytrap/until_parser_test.py
flytrap/with_parser.py
flytrap/with_parser_test.py
flytrap_py-0.1.4.dist-info/LICENSE
flytrap_py-0.1.4.dist-info/METADATA
flytrap_py-0.1.4.dist-info/WHEEL
flytrap_py-0.1.4.dist-info/entry_points.txt
flytrap_py-0.1.4.dist-info/RECORD
